{
   "files": [   
      
   {
         "name": "SG-D-T-NOPRO01",
         "url": "https://raw.githubusercontent.com/Nookerzex/Nookerzex/main/SG-D-T-NOPRO01.ovpn"
      },
      {
         "name": "SG-D-T-NOPRO02",
         "url": "https://raw.githubusercontent.com/Nookerzex/Nookerzex/main/SG-D-T-NOPRO02.ovpn"
      }

      


   ],
"message":" Support Simcard \n\n Dtac NoPro..\n True NoPro....\n\n Nooker net \n By: Nooker\n ",
   "title":"ไฟล์อัพเดทใหม่พร้อมใช้งาน" ,
   "version": 1.4
}
